sidai/__init__.py
sidai/connect.py
sidai-0.1.1.dist-info/LICENSE
sidai-0.1.1.dist-info/METADATA
sidai-0.1.1.dist-info/WHEEL
sidai-0.1.1.dist-info/top_level.txt
sidai-0.1.1.dist-info/RECORD
