Metadata-Version: 2.1
Name: sidai
Version: 0.1.1
Summary: Python wrapper for the SID API
Author: Georgijs Vilums
License: Permission is hereby granted, free of charge, to any
License-File: LICENSE
Requires-Dist: httpx >=0.25.0
Requires-Dist: dataclass-wizard >=0.22.0
